autograd/__init__.py
autograd/config.py
autograd/functions.py
autograd/node.py
autograd/optimize.py
autograd/utils.py
autograd/variable.py
autograd/blocks/__init__.py
autograd/blocks/block.py
autograd/blocks/expo.py
autograd/blocks/hyperbolic.py
autograd/blocks/operations.py
autograd/blocks/trigo.py
dragongrad-1.2.dist-info/LICENSE
dragongrad-1.2.dist-info/METADATA
dragongrad-1.2.dist-info/WHEEL
dragongrad-1.2.dist-info/top_level.txt
dragongrad-1.2.dist-info/RECORD
