Metadata-Version: 2.1
Name: dragongrad
Version: 1.2
Summary: Automatic Differentiation Library
Home-page: https://github.com/cs207-project-group4/cs207-FinalProject
Author: cs207-project-group4
Author-email: dylanrandle@gmail.com
License: UNKNOWN
Platform: UNKNOWN
Classifier: Programming Language :: Python :: 3
Classifier: License :: OSI Approved :: MIT License
Classifier: Operating System :: OS Independent
